maitai/__init__.py
maitai/_config.py
maitai/_config_listener.py
maitai/_context.py
maitai/_evaluator.py
maitai/_inference.py
maitai/_maitai.py
maitai/_maitai_async.py
maitai/_maitai_client.py
maitai/_pydantic.py
maitai/_types.py
maitai/_utils.py
maitai/exceptions.py
maitai/agent/__init__.py
maitai/agent/_completions.py
maitai/agent/_completions_async.py
maitai/chat/__init__.py
maitai/chat/_completions.py
maitai/chat/_completions_async.py
maitai/models/__init__.py
maitai/models/agent_action.py
maitai/models/agent_routing.py
maitai/models/application.py
maitai/models/chat.py
maitai/models/config.py
maitai/models/event.py
maitai/models/inference.py
maitai/models/key.py
maitai/models/metric.py
maitai/models/sentinel.py
maitai/models/agent/__init__.py
maitai/models/agent/base.py
maitai/models/agent/enum.py
maitai/models/agent/extended.py
maitai/tools/__init__.py
maitai/transcriptions/__init__.py
maitai/transcriptions/_transcriptions.py
maitai/transcriptions/_transcriptions_async.py
maitai_common/__init__.py
maitai_common/version.py
maitai_common/config/__init__.py
maitai_common/config/config_service.py
maitai_python-1.2.30.dist-info/METADATA
maitai_python-1.2.30.dist-info/WHEEL
maitai_python-1.2.30.dist-info/top_level.txt
maitai_python-1.2.30.dist-info/RECORD
