Metadata-Version: 2.4
Name: maitai-python
Version: 1.2.30
Summary: Maitai SDK for Python
Home-page: https://docs.trymaitai.ai
Author: Maitai
Author-email: support@trymaitai.ai
License: MIT
Classifier: Programming Language :: Python :: 3
Classifier: License :: OSI Approved :: MIT License
Requires-Dist: openai>=1.34.0
Requires-Dist: httpx[http2]
Requires-Dist: websocket-client
Requires-Dist: pyhumps
Requires-Dist: pydantic>=2.0.0
Requires-Dist: groq
Dynamic: author
Dynamic: author-email
Dynamic: classifier
Dynamic: description
Dynamic: description-content-type
Dynamic: home-page
Dynamic: license
Dynamic: requires-dist
Dynamic: summary
